{
    "power_menu": [
        40,
        310
    ],
    "dup_menu": [
        47,
        536
    ],
    "research_menu": [
        50,
        580
    ],
    "research_window": [
        181,
        643
    ],
    "research_button": [
        178,
        738
    ],
    "time_menu": [],
    "a1_slot": [],
    "e0_slot": [],
    "een": [
        -1283,
        122
    ],
    "twee": [
        -1283,
        161
    ],
    "drie": [
        -1283,
        200
    ],
    "vier": [
        -1283,
        239
    ],
    "vijf": [
        -1283,
        278
    ],
    "zes": [
        -1283,
        317
    ]
}